YTMusicPy/__init__.py
YTMusicPy/music.py
YTMusicInfo-0.0.1.dist-info/METADATA
YTMusicInfo-0.0.1.dist-info/WHEEL
YTMusicInfo-0.0.1.dist-info/top_level.txt
YTMusicInfo-0.0.1.dist-info/RECORD
