Metadata-Version: 2.1
Name: YTMusicInfo
Version: 0.0.1
Summary: YTMusicPY is an API wrapper for the YTMDesktop remote (https://github.com/ytmdesktop/ytmdesktop/)
Home-page: UNKNOWN
Author: T1ps
Author-email: quintindunn67@gmail.com
License: UNKNOWN
Keywords: python,youtube,music,player,YTMAPI,api
Platform: UNKNOWN
Requires-Dist: requests
